oasis_rofl_client/__about__.py
oasis_rofl_client/__init__.py
oasis_rofl_client/_version.py
oasis_rofl_client/async_rofl_client.py
oasis_rofl_client/common.py
oasis_rofl_client/rofl_client.py
oasis_rofl_client-0.2.0.dist-info/METADATA
oasis_rofl_client-0.2.0.dist-info/WHEEL
oasis_rofl_client-0.2.0.dist-info/RECORD
