Metadata-Version: 2.4
Name: oasis-rofl-client
Version: 0.2.0
Summary: Python client SDK for Oasis ROFL.
Project-URL: Homepage, https://github.com/oasisprotocol/oasis-sdk/tree/main/rofl-client/py
Project-URL: Repository, https://github.com/oasisprotocol/oasis-sdk/tree/main/rofl-client/py
Project-URL: Issue_tracker, https://github.com/oasisprotocol/oasis-sdk/issues
Author-email: rube-de <bernhard@oasisprotocol.org>
License: Apache-2.0
Keywords: client,oasis,rofl,sdk
Classifier: License :: OSI Approved :: Apache Software License
Classifier: Operating System :: OS Independent
Classifier: Programming Language :: Python :: 3
Classifier: Programming Language :: Python :: 3.9
Classifier: Programming Language :: Python :: 3.10
Classifier: Programming Language :: Python :: 3.11
Classifier: Programming Language :: Python :: 3.12
Classifier: Typing :: Typed
Requires-Python: >=3.9
Requires-Dist: cbor2>=5.7.1
Requires-Dist: httpx>=0.25.0
Requires-Dist: web3>=7.14.0
